<?xml version="1.0" encoding="utf-8" ?>
<dwsync>
<file name="P2270002.jpg" local="131014944000000000" remote="131014944000000000" testing="0" />
<file name="P2270008.jpg" local="131014944000000000" remote="131014944000000000" testing="0" />
<file name="P2270011.jpg" local="131014944000000000" remote="131014944000000000" testing="0" />
<file name="P2270023.jpg" local="131014944000000000" remote="131014944000000000" testing="0" />
<file name="P2270027.jpg" local="131014944000000000" remote="131014944000000000" testing="0" />
<file name="P2270033.jpg" local="131014944000000000" remote="131014944000000000" testing="0" />
<file name="P2280034.jpg" local="131014944000000000" remote="131014944000000000" testing="0" />
<file name="P2280035.jpg" local="131014944000000000" remote="131014944000000000" testing="0" />
<file name="P2280043.jpg" local="131014944000000000" remote="131014944000000000" testing="0" />
<file name="P2280052.jpg" local="131014944000000000" remote="131014944000000000" testing="0" />
<file name="P2280053.jpg" local="131014944000000000" remote="131014944000000000" testing="0" />
<file name="P2280055.jpg" local="131014944000000000" remote="131014944000000000" testing="0" />
</dwsync>